pymicro365
